qode_task_worker/__init__.py
qode_task_worker/config.py
qode_task_worker/rabbitmq_worker.py
qode_task_worker/task_client.py
qode_task_worker/task_worker.py
qode_task_worker-1.0.4.dist-info/licenses/LICENSE
qode_task_worker-1.0.4.dist-info/METADATA
qode_task_worker-1.0.4.dist-info/WHEEL
qode_task_worker-1.0.4.dist-info/top_level.txt
qode_task_worker-1.0.4.dist-info/RECORD
