Metadata-Version: 2.4
Name: qode-task-worker
Version: 1.0.4
Summary: A Python library for task management with RabbitMQ and polling support
Author: Bao Ninh
Author-email: Bao Ninh <bao.ninh@qode.world>
Maintainer: Bao Ninh
Maintainer-email: Bao Ninh <bao.ninh@qode.world>
License-Expression: MIT
Keywords: task,worker,rabbitmq,polling,queue
Classifier: Development Status :: 4 - Beta
Classifier: Intended Audience :: Developers
Classifier: Operating System :: OS Independent
Classifier: Programming Language :: Python :: 3
Classifier: Programming Language :: Python :: 3.8
Classifier: Programming Language :: Python :: 3.9
Classifier: Programming Language :: Python :: 3.10
Classifier: Programming Language :: Python :: 3.11
Classifier: Programming Language :: Python :: 3.12
Requires-Python: >=3.8
License-File: LICENSE
Requires-Dist: requests>=2.25.0
Requires-Dist: pika>=1.2.0
Dynamic: license-file
